shuttlet_claude_opus/__init__.py
shuttlet_claude_opus-0.1.0.dist-info/WHEEL
shuttlet_claude_opus-0.1.0.dist-info/entry_points.txt
shuttlet_claude_opus-0.1.0.dist-info/METADATA
shuttlet_claude_opus-0.1.0.dist-info/RECORD
