Metadata-Version: 2.3
Name: shuttlet_claude_opus
Version: 0.1.0
Summary: Claude Opus MCP Server - 基于 OpenAI 兼容 API 的 Claude 聊天服务
Author: entelin
Author-email: entelin <entelin@tencent.com>
Requires-Dist: mcp[cli]>=1.25.0
Requires-Dist: requests>=2.32.5
Requires-Python: >=3.10
